pdcleaner/__init__.py
pdcleaner/__version__.py
pdcleaner/cleaning/__init__.py
pdcleaner/cleaning/cleaning.py
pdcleaner/detection/__init__.py
pdcleaner/detection/_base.py
pdcleaner/detection/basic.py
pdcleaner/detection/by_category.py
pdcleaner/detection/datetimes.py
pdcleaner/detection/gaussian.py
pdcleaner/detection/multivariate.py
pdcleaner/detection/strings.py
pdcleaner/detection/types.py
pdcleaner/detection/values.py
pdcleaner/detection/web.py
pdcleaner/plots/__init__.py
pdcleaner/plots/alternatives.py
pdcleaner/plots/freqandcount.py
pdcleaner/plots/multicategories.py
pdcleaner/plots/numseries.py
pdcleaner/utils/__init__.py
pdcleaner/utils/df_utils.py
pdcleaner/utils/report_utils.py
pdcleaner/utils/utils.py
pandas_cleaner-0.0.3.dist-info/LICENSE
pandas_cleaner-0.0.3.dist-info/METADATA
pandas_cleaner-0.0.3.dist-info/WHEEL
pandas_cleaner-0.0.3.dist-info/top_level.txt
pandas_cleaner-0.0.3.dist-info/RECORD
