Metadata-Version: 2.1
Name: pandas-cleaner
Version: 0.0.3
Summary: A pandas extension for cleaning datasets.
Home-page: https://github.com/eurodecision/pandas-cleaner
Author: Renan Hilbert
Author-email: renan.hilbert@eurodecision.com
License: UNKNOWN
Project-URL: Documentation, https://pandas-cleaner.readthedocs.io/
Project-URL: Source Code, https://github.com/eurodecision/pandas-cleaner
Project-URL: Bug Tracker, https://github.com/eurodecision/pandas-cleaner/issues
Platform: UNKNOWN
Classifier: Programming Language :: Python :: 3
Classifier: Operating System :: OS Independent
Classifier: License :: OSI Approved :: BSD License
Classifier: Intended Audience :: Science/Research
Classifier: Intended Audience :: Developers
Classifier: Programming Language :: Python
Classifier: Topic :: Software Development
Classifier: Topic :: Scientific/Engineering
Requires-Python: >=3.6
Requires-Dist: numpy
Requires-Dist: pandas
Requires-Dist: matplotlib
Requires-Dist: seaborn
Requires-Dist: scikit-learn
Requires-Dist: requests
